{"note":"This file is an internal implementation detail to speed up HTML report generation. Its format can change at any time. You might be looking for the JSON report: https://coverage.rtfd.io/cmd.html#cmd-json","format":5,"version":"7.11.3","globals":"51a9fb749f9a4e7e6905eef8910dc5b3","files":{"z_289cdd568d385b86___init___py":{"hash":"4b20ac79470d2badf507511c164fa752","index":{"url":"z_289cdd568d385b86___init___py.html","file":"src/bwd/__init__.py","description":"","nums":{"precision":0,"n_files":1,"n_statements":4,"n_excluded":0,"n_missing":0,"n_branches":0,"n_partial_branches":0,"n_missing_branches":0}}},"z_289cdd568d385b86_bwd_py":{"hash":"0aa03f646ce42a5008f00bdd9fdee606","index":{"url":"z_289cdd568d385b86_bwd_py.html","file":"src/bwd/bwd.py","description":"","nums":{"precision":0,"n_files":1,"n_statements":61,"n_excluded":0,"n_missing":1,"n_branches":0,"n_partial_branches":0,"n_missing_branches":0}}},"z_289cdd568d385b86_bwd_random_py":{"hash":"6cf56ba6f80c6cd50e025f86f2a08f52","index":{"url":"z_289cdd568d385b86_bwd_random_py.html","file":"src/bwd/bwd_random.py","description":"","nums":{"precision":0,"n_files":1,"n_statements":50,"n_excluded":0,"n_missing":1,"n_branches":0,"n_partial_branches":0,"n_missing_branches":0}}},"z_289cdd568d385b86_exceptions_py":{"hash":"d6e8f1551e5a398f46ee1f74de6470c4","index":{"url":"z_289cdd568d385b86_exceptions_py.html","file":"src/bwd/exceptions.py","description":"","nums":{"precision":0,"n_files":1,"n_statements":1,"n_excluded":0,"n_missing":0,"n_branches":0,"n_partial_branches":0,"n_missing_branches":0}}},"z_289cdd568d385b86_multi_bwd_py":{"hash":"6801fbb7a079a87a2f640a34cf260d08","index":{"url":"z_289cdd568d385b86_multi_bwd_py.html","file":"src/bwd/multi_bwd.py","description":"","nums":{"precision":0,"n_files":1,"n_statements":87,"n_excluded":0,"n_missing":4,"n_branches":0,"n_partial_branches":0,"n_missing_branches":0}}},"z_289cdd568d385b86_online_py":{"hash":"028ea30037ef24e34cf3c3d3d7991702","index":{"url":"z_289cdd568d385b86_online_py.html","file":"src/bwd/online.py","description":"","nums":{"precision":0,"n_files":1,"n_statements":29,"n_excluded":0,"n_missing":17,"n_branches":0,"n_partial_branches":0,"n_missing_branches":0}}},"z_289cdd568d385b86_serialization_py":{"hash":"272b055dcbd82bacd3c9d46898fb7cc3","index":{"url":"z_289cdd568d385b86_serialization_py.html","file":"src/bwd/serialization.py","description":"","nums":{"precision":0,"n_files":1,"n_statements":25,"n_excluded":0,"n_missing":0,"n_branches":0,"n_partial_branches":0,"n_missing_branches":0}}}}}